{
    "id": 2062,
    "japanese": "～たところ",
	"meanings": [
	{
		"meaning": "～たら＜あることをしたら、その結果がどうなったかを表す表現＞",
		"translation": "",
		"forms":["「動た形」＋ところ"],
	}
	]
	"excludes": [""],
	"notes": "例：",
	"examples": [
		{
			"japanese": "病院で検査したところ、異常はなかった。",
			"reading": "びょういん　で　けんさした　ところ、いじょう　は　なかった。",
			"translation": "Когда я обследовался в больнице, не было ничего необычного."
		},
		{
			"japanese": "駅に問い合わせたところ、忘れ物は届いていた。",
			"reading": "えき　に　といあわせた　ところ、わすれもの　は　とどいて　いた。",
			"translation": "Когда я спросил на станции, мне вернули забытую вещь."
		},
		{
			"japanese": "新しいワープロを使ってみたところ、とても使いやすかった。",
			"reading": "あたらしい　ワープロ　を　つかって　みた　ところ、とても　つかいやすかった。",
			"translation": "Попробовал новую печатную машинку, очень легко пользоваться."
		},
		{
			"japanese": "コンピュータが動かず、どうしていいか困っていたところ、山田さんが助けてくれた。",
			"reading": "コンピュータ　が　うごかず、どうして　いい　か　こまっていた　ところ、やまださん　が　たすけて　くれた。",
			"translation": "Компьютер не запускался, когда думал, что же делать, Ямада помог."
		}
	],
	"references":["put ids of reference here"]
}
