{
    "id": 2047,
    "japanese": "～につれて・～につれ",
	"meanings": [
	{
		"meaning": "～といっしょに＜一方変化とともに他方も変わることを表す＞",
		"translation": "",
		"forms":["「動辞書形・名」＋につれて"],
	}
	]
	"excludes": ["だめ：予定表につれて"],
	"notes": "例：",
	"examples": [
		{
			"japanese": "年を取るにつれて、体のいろいろな機能が低下する。",
			"reading": "とし　を　とる　に　つれて、からだ　の　いろりろな　きのう　が　ていかする。",
			"translation": "С возрастом различные функции организма ухудшаются."
		},
		{
			"japanese": "町の発展につれて、自然が少なくなった。",
			"reading": "まち　の　はってん　に　つれて、しぜん　が　すくなく　なった。",
			"translation": "С развитием города зелени становится меньше."
		},
		{
			"japanese": "品質がよくなるにつれて、値段が高くなる。",
			"reading": "ひんしつ　が　よくなる　に　つれて、ねだん　が　たかく　なる。",
			"translation": "По мере улучшения качества цена становится выше."
		},
		{
			"japanese": "時代の変化につれて、結婚の形も変わってきた。",
			"reading": "じだい　の　へんか　に　つれて、けっこん　の　かたち　も　かわって　きた。",
			"translation": "Вместе со сменой эпох изменилась и форма брака."
		},
		{
			"japanese": "年をとるにつれ、昔のことがなつかしく思い出される。",
			"reading": "とし　を　とる　に　つれて、むかし　の　こと　が　なつかしく　おいおだされる。",
			"translation": "С годами старое вспоминается с ностальгией."
		}
	],
	"references":["put ids of reference here"]
}
