{
    "id": 2065,
    "japanese": "",
	"meanings": [
	{
		"meaning": "",
		"translation": "",
		"forms":[""],
	}
	]
	"excludes": [""],
	"notes": "例：",
	"examples": [
		{
			"japanese": "「夏休みは取れそう？」「忙しくて夏休みどころか日曜日も休みないよ。」「そう。うちの会社は忙しいどころか仕事がなくて困っているんだ。」",
			"reading": "「なつやすみ　とれそう？」「いそがしくて　なつやすみ　どころか　にちようび　も　やすみないよ。」「そう。　うち　の　かいしゃ　は　いそがしい　どころか　しごと　が　なくて　こまって　いるんだ。」",
			"translation": "'Летний отпуск думаешь брать?' 'Очень занят, не то что летний отпуск, даже в воскресенье не отдыхаю.' 'Вот как. На моей работе не то, что занят, вообще работы нет, проблема'."
		},
		{
			"japanese": "彼は貯金するどころか借金だらけだ。",
			"reading": "かれ　は　ちょきんする　どころか　しゃっきん　だらけだ。",
			"translation": "Он не то что не откладывает деньги, но и весь в долгах."
		},
		{
			"japanese": "この部屋は涼しいどころか寒いくらいだ。",
			"reading": "この　へや　は　すずしい　どころか　さむい　くらい　だ。",
			"translation": "В этой комнате не прохладно, а даже холодно."
		},
		{
			"japanese": "「お宅の辺りは静かでしょう。」「いいえ、静かどころか最近は窓を開けていられないほど車の音がうるさいんです。」",
			"reading": "「おたく　の　あたり　は　しずか　でしょう。」「いいえ、しずか　どころか　さいきん　は　まど　を　あけて　いられない　ほど　くるま　の　おと　が　うるさい　んです。」",
			"translation": "'Ты живешь в тихом месте?' 'Нет, не то чтобы тихо, последнее время даже окно не могу открыть, такой шум от машин.'"
		},
		{
			"japanese": "あの人は英語どころかアラビア語もスアヒリ語も話せる。",
			"reading": "あの　ひと　は　えいご　どころか　アラビアご　も　スアヒリご　も　はなせる。",
			"translation": "Тот человек не то что по-английски, но и по арабски и на суахили может разговаривать."
		}
	],
	"references":["put ids of reference here"]
}
