{
    "id": 2042,
    "japanese": "～としたら・～とすれば",
	"meanings": [
	{
		"meaning": "～なら＜仮定の表現＞",
		"translation": "если, допустим",
		"forms":["「動・い形・な形・名」の普通形＋としたら"],
	},
	{
		"meaning": "～なら・～から考えれば",
		"translation": "если (с точки зрения кого-то)",
		"forms":["「動・い形・な形・名」の普通形＋としたら"],
	}
	]
	"excludes": [""],
	"notes": "例：",
	"examples": [
		{
			"japanese": "もし、それが本当だとしたら、夢のようです。",
			"reading": "もし、それ　が　ほんとう　だ　としたら、ゆめ　の　よう　です。",
			"translation": "Если это правда, то это как сон."
		},
		{
			"japanese": "あの人が今も生きているとすれば、もう９０歳になっているでしょう。",
			"reading": "あの　ひと　が　いま　も　いきている　とすれば、もう　９０さい　に　なっている　でしょう。",
			"translation": "Если бы этот человек был сейчас жив, ему было бы уже 90 лет."
		},
		{
			"japanese": "留学するとしたら、日本に行きたいと思っていました。",
			"reading": "りゅうがくする　としたら、にほん　に　いきたい　と　おもっています。",
			"translation": "Если уж учиться за рубежом, то я хотел поехать в Японию."
		},
		{
			"japanese": "もし、もう一度生まれ変わるとしたら、男と女とどちらがいいですか。",
			"reading": "もし、もう　いちど　うまれかわる　としたら、おとこ　と　おんな　と　どちら　が　いい　ですか。",
			"translation": "Если бы ты еще раз родился, кем бы хотел быть: мужчиной или женщиной?"
		},
		{
			"japanese": "予定どおりだとすれば、飛行機は９時に着くはずだ。",
			"reading": "よてい　どおり　だ　とすれば、ひこうき　は　９じ　に　つく　はず　だ。",
			"translation": "По расписанию самолет должен прибыть в 9 часов."
		},
		{
			"japanese": "足の悪い人が地下鉄を利用するとしたら、どんな準備が必要だろうか。",
			"reading": "あし　の　わるい　ひと　が　ちかてつ　を　りようする　としたら、どんな　設備　が　ひつよう　だろうか。",
			"translation": "Если учесть, что люди с больными ногами пользуются метро, то какие приспособления необходимы?"
		},
		{
			"japanese": "「この冷蔵庫はもう修理は無理ですね。」「修理が無理だとしたら、新しいのを買うしかありませんね。」",
			"reading": "「この　れおぞうこ　は　もう　しゅうり　は　むり　ですね。」「しゅうり　が　むり　だ　としたら、あたらしい　の　を　かう　しか　ありませんね。」",
			"translation": "Этот холодильник невозможно починить. Если невозможно починить, остается только купить новый."
		},
		{
			"japanese": "電話をかけても、出ないとすれば、彼はもう出かけたのでしょう。",
			"reading": "でんわ　を　かけても、でない　とすれば、かれ　は　もう　でかけた　の　でしょう。",
			"translation": "Если Вы звоните, а он не выходит, то наверное он уже ушел."
		}
	],
	"references":["put ids of reference here"]
}
