{
	"words": [
	{
		"word": {
			"japanese": "ホームヘルパー",
			"reading": "ホームヘルパー",
			"translation": "сиделка, работник по уходу на дому"
		},
		"expressions": [
			{
				"japanese": "老人ホームのホームヘルパー",
				"reading": "ろうじんホームのホームヘルパー",
				"translation": "сиделка в доме престарелых"
			}
		]
	},
	{
		"word": 
		{
			"japanese": "講師",
			"reading": "こうし",
			"translation": "лектор, инструктор"
		},
		"expressions": [
			{
				"japanese": "語学学校の講師",
				"reading": "ごがくがっこうのこうし",
				"translation": "преподаватель в языковой школе"
			}
		]
	},
	{
		"word": 
		{
			"japanese": "事務員",
			"reading": "じむいん",
			"translation": "клерк"
		},
		"expressions": [
			{
				"japanese": "会社の事務員",
				"reading": "かいしゃのじむいん",
				"translation": "клерк, офисный работник"
			}
		]
	},
	{
		"word": 
		{
			"japanese": "関係",
			"reading": "かんけい",
			"translation": "отношение, связь"
		},
		"expressions": [
			{
				"japanese": "コンピューター関係の仕事",
				"reading": "コンピューターかんけいのしごと",
				"translation": "работа, связанная с IT"
			}
		]
	},
	{
		"word": 
		{
			"japanese": "オーナー",
			"reading": "オーナー",
			"translation": "владелец"
		},
		"expressions": [
			{
				"japanese": "レストランのオーナー",
				"reading": "レストランのオーナー",
				"translation": "владелец ресторана"
			}
		]
	},
	{
		"word": 
		{
			"japanese": "従業員",
			"reading": "じゅうぎょういん",
			"translation": "служащий, работник"
		},
		"expressions": [
			{
				"japanese": "ホテルの従業員",
				"reading": "ホテルのじゅうぎょういん",
				"translation": "работник отеля"
			}
		]
	},
	{
		"word": 
		{
			"japanese": "フリーター",
			"reading": "フリーター",
			"translation": "человек без постоянной работы, живет на подработки"
		}
	},
	{
		"word": 
		{
			"japanese": "就職する",
			"reading": "しゅうしょくする",
			"translation": "поступление на работу"
		},
		"expressions": [
			{
				"japanese": "就職活動",
				"reading": "しゅうしょくかつどう",
				"translation": "искать работу"
			}
		]
	},
	{
		"word": 
		{
			"japanese": "求人",
			"reading": "きゅうじん",
			"translation": "предложение работы (ситуация), требуется работник"
		},
		"expressions": [
			{
				"japanese": "求人情報",
				"reading": "きゅうじんじょうほう",
				"translation": "информация о вакансиях"
			}
		]
	},
	{
		"word": 
		{
			"japanese": "履歴書",
			"reading": "りれきしょ",
			"translation": "автобиография, резюме"
		},
		"expressions": [
			{
				"japanese": "履歴書を書く",
				"reading": "りれきしょをかく",
				"translation": "писать резюме"
			}
		]
	},
	{
		"word": 
		{
			"japanese": "制限",
			"reading": "せいげん",
			"translation": "ограничение, лимит"
		},
		"expressions": [
			{
				"japanese": "年齢制限がある",
				"reading": "ねんれいせいげんがある",
				"translation": "возраст ограничен"
			}
		]
	},
	{
		"word": 
		{
			"japanese": "問わない",
			"reading": "とわない",
			"translation": "не придавать значения"
		},
		"expressions": [
			{
				"japanese": "経験を問わない",
				"reading": "けいけんをとわない",
				"translation": "опыт работы не требуется"
			}
		]
	},
	{
		"word": 
		{
			"japanese": "やとう",
			"reading": "やとう",
			"translation": "нанимать, принимать на работу"
		}
	},
	{
		"word": 
		{
			"japanese": "採用する",
			"reading": "さいようする",
			"translation": "нанимать, принимать на работу"
		}
	},
	{
		"word": 
		{
			"japanese": "人手",
			"reading": "ひとで",
			"translation": "рабочие руки"
		}
	},
	{
		"word": 
		{
			"japanese": "不足",
			"reading": "ふそく",
			"translation": "недостаток, нехватка, недовольство"
		},
		"expressions": [
			{
				"japanese": "人手が不足している",
				"reading": "ひとでがふそくしている",
				"translation": "не хватает рабочих рук"
			},
			{
				"japanese": "不足を言う",
				"reading": "ふそくをいう",
				"translation": "выражать недовольство"
			}
		]
	},
	{
		"word": 
		{
			"japanese": "正社員",
			"reading": "せいしゃいん",
			"translation": "штатный сотрудник, полноправный член"
		}
	},
	{
		"word": 
		{
			"japanese": "募集",
			"reading": "ぼしゅう",
			"translation": "вербовка, набор, комплектование"
		},
		"expressions": [
			{
				"japanese": "正社員を募集する",
				"reading": "せいしゃいんをぼしゅうする",
				"translation": "объявлять набор в штат"
			}
		]
	},
	{
		"word": 
		{
			"japanese": "派遣社員",
			"reading": "はけんしゃいん",
			"translation": "временный работник"
		}
	},
	{
		"word": 
		{
			"japanese": "登録",
			"reading": "とうろく",
			"translation": "регистрация, запись"
		},
		"expressions": [
			{
				"japanese": "派遣社員に登録する",
				"reading": "はけんしゃいんにとうろくする",
				"translation": "регистрироваться временным работником"
			}
		]
	},
	{
		"word": 
		{
			"japanese": "問い合わせる",
			"reading": "といあわせる",
			"translation": "наводить справки, осведомляться"
		},
		"expressions": [
			{
				"japanese": "会社に問い合わせる",
				"reading": "かいしゃにといあわせる",
				"translation": "спрашивать компанию о"
			}
		]
	},
	{
		"word": 
		{
			"japanese": "気軽に",
			"reading": "きがるに",
			"translation": "легко, непринужденно"
		},
		"expressions": [
			{
				"japanese": "気軽に尋ねる",
				"reading": "きがるにたずねる",
				"translation": "задавайте любые вопросы"
			}
		]
	},
	{
		"word": 
		{
			"japanese": "面接",
			"reading": "めんせつ",
			"translation": "собеседование"
		}
	},
	{
		"word": 
		{
			"japanese": "緊張",
			"reading": "きんちょう",
			"translation": "напряженность, натянутость"
		},
		"expressions": [
			{
				"japanese": "面接で緊張する",
				"reading": "めんせつできんちょうする",
				"translation": "нервничать на собеседовании"
			}
		]
	},
	{
		"word": 
		{
			"japanese": "相応しい",
			"reading": "ふさわしい",
			"translation": "подходящий, соответствующий"
		}
	},
	{
		"word": 
		{
			"japanese": "服装",
			"reading": "ふくそう",
			"translation": "одежда, форма"
		},
		"expressions": [
			{
				"japanese": "面接にふさわしい服装",
				"reading": "めんせつにふさわしいふくそう",
				"translation": "подходящая для собеседования одежда"
			}
		]
	},
	{
		"word": 
		{
			"japanese": "勤務",
			"reading": "きんむ",
			"translation": "служба, служебные обязанности"
		},
		"expressions": [
			{
				"japanese": "８時間勤務",
				"reading": "８じかんきんむ",
				"translation": "8-ми часовой рабочий день"
			}
		]
	},
	{
		"word": 
		{
			"japanese": "時給",
			"reading": "じきゅう",
			"translation": "заработная плата за час"
		},
		"expressions": [
			{
				"japanese": "時給で働く",
				"reading": "じきゅうではたらく",
				"translation": "работать с почасовой оплатой"
			}
		]
	},
	{
		"word": 
		{
			"japanese": "支給",
			"reading": "しきゅう",
			"translation": "снабжение, выплата"
		},
		"expressions": [
			{
				"japanese": "交通費が支給される",
				"reading": "こうつうひがしきゅうされる",
				"translation": "транспортные расходы возмещаются"
			},
			{
				"japanese": "服装を支給する",
				"reading": "ふくそうをしきゅうする",
				"translation": "снабжать одеждой"
			}
		]
	},
	{
		"word": 
		{
			"japanese": "かせぐ",
			"reading": "かせぐ",
			"translation": "зарабатывать"
		},
		"expressions": [
			{
				"japanese": "お金をかせぐ",
				"reading": "おかねをかせぐ",
				"translation": "зарабатывать деньги"
			}
		]
	},
	{
		"word": 
		{
			"japanese": "もうける",
			"reading": "もうける",
			"translation": "зарабатывать, наживаться, выгадывать"
		},
		"expressions": [
			{
				"japanese": "お金をもうける",
				"reading": "おかねをもうける",
				"translation": "зарабатывать много денег"
			},
			{
				"japanese": "店がもうかる",
				"reading": "みせがもうける",
				"translation": "магазин очень прибыльный"
			}
		]
	}
	]
}